{
  "id": 21187631,
  "name": "Altergeist Dragvirion",
  "is_illegal": false,
  "is_custom": false,
  "text": "1 Tuner + 1+ non-Tuner monsters\nWhen an opponent's Special Summoned monster declares an attack: You can return 1 \"Altergeist\" monster you control to the hand; negate that attack. If this card is Tributed and sent to the GY: You can Special Summon this card. You can only use each effect of \"Altergeist Dragvirion\" once per turn.",
  "images": [
    "h",
    "t",
    "t",
    "p",
    "s",
    ":",
    "/",
    "/",
    "i",
    "m",
    "a",
    "g",
    "e",
    "s",
    ".",
    "y",
    "g",
    "o",
    "p",
    "r",
    "o",
    "d",
    "e",
    "c",
    "k",
    ".",
    "c",
    "o",
    "m",
    "/",
    "i",
    "m",
    "a",
    "g",
    "e",
    "s",
    "/",
    "c",
    "a",
    "r",
    "d",
    "s",
    "/",
    "2",
    "1",
    "1",
    "8",
    "7",
    "6",
    "3",
    "1",
    ".",
    "j",
    "p",
    "g"
  ],
  "type": "Monster",
  "attribute": "DARK",
  "atk": 2200,
  "species": "Spellcaster",
  "ability": "Synchro",
  "has_effect": true,
  "is_pendulum": false,
  "monster_type": "Synchro",
  "def": 1200,
  "level": 6,
  "is_tuner": false
}