{
  "id": 28531163,
  "name": "Apocaries",
  "is_illegal": false,
  "is_custom": false,
  "text": "When this card is activated: Place Caries Counters on this card equal to the number of cards your opponent controls. You can target 1 face-up monster your opponent controls and remove up to 4 Caries Counters from your field; apply this effect to that monster based on the number removed.\r\n● 1: It loses 500 ATK.\r\n● 2: Change its ATK to 0.\r\n● 3: Negate its effects.\r\n● 4: Destroy it.\r\nYou can only activate 1 \"Apocaries\" per turn.",
  "images": [
    "https://images.ygoprodeck.com/images/cards/28531163.jpg"
  ],
  "type": "Spell",
  "spell_type": "Continuous"
}