{
  "id": 2148918,
  "name": "Armor Ninjitsu Art of Rust Mist",
  "is_illegal": false,
  "is_custom": false,
  "text": "When a monster(s) is Special Summoned to your opponent's field, if you control a \"Ninja\" monster: Halve the current ATK of that Special Summoned monster(s).",
  "images": [
    "h",
    "t",
    "t",
    "p",
    "s",
    ":",
    "/",
    "/",
    "i",
    "m",
    "a",
    "g",
    "e",
    "s",
    ".",
    "y",
    "g",
    "o",
    "p",
    "r",
    "o",
    "d",
    "e",
    "c",
    "k",
    ".",
    "c",
    "o",
    "m",
    "/",
    "i",
    "m",
    "a",
    "g",
    "e",
    "s",
    "/",
    "c",
    "a",
    "r",
    "d",
    "s",
    "/",
    "2",
    "1",
    "4",
    "8",
    "9",
    "1",
    "8",
    ".",
    "j",
    "p",
    "g"
  ],
  "type": "Trap",
  "trap_type": "Continuous"
}