{
  "id": 48582558,
  "name": "Bounzer Guard",
  "is_illegal": false,
  "is_custom": false,
  "text": "Target 1 face-up \"Bounzer\" monster you control; this turn, it cannot be targeted by other card effects, or be destroyed by battle. This turn, if an opponent's monster attacks, it must target that monster for an attack if it is still on the field.",
  "images": [
    "h",
    "t",
    "t",
    "p",
    "s",
    ":",
    "/",
    "/",
    "i",
    "m",
    "a",
    "g",
    "e",
    "s",
    ".",
    "y",
    "g",
    "o",
    "p",
    "r",
    "o",
    "d",
    "e",
    "c",
    "k",
    ".",
    "c",
    "o",
    "m",
    "/",
    "i",
    "m",
    "a",
    "g",
    "e",
    "s",
    "/",
    "c",
    "a",
    "r",
    "d",
    "s",
    "/",
    "4",
    "8",
    "5",
    "8",
    "2",
    "5",
    "5",
    "8",
    ".",
    "j",
    "p",
    "g"
  ],
  "type": "Trap",
  "trap_type": "Normal"
}