{
  "id": 15635751,
  "name": "Camelot, Realm of Noble Knights and Noble Arms",
  "is_illegal": false,
  "is_custom": false,
  "text": "Once per turn, if a \"Noble Knight\" card(s) you control would be destroyed by battle or card effect, you can destroy 1 Equip Card you control instead. During your Main Phase: You can banish this card (until the next Standby Phase), and if you do, place 1 \"Noble Knights of the Round Table\" from your hand, Deck, or GY, face-up in your Field Zone, then you can Special Summon 1 \"Artorigus\" monster, or add to your hand 1 \"Noble Arms\" card, from your Deck or GY. You can only use this effect of \"Camelot, Realm of Noble Knights and Noble Arms\" once per turn.",
  "images": [
    "h",
    "t",
    "t",
    "p",
    "s",
    ":",
    "/",
    "/",
    "i",
    "m",
    "a",
    "g",
    "e",
    "s",
    ".",
    "y",
    "g",
    "o",
    "p",
    "r",
    "o",
    "d",
    "e",
    "c",
    "k",
    ".",
    "c",
    "o",
    "m",
    "/",
    "i",
    "m",
    "a",
    "g",
    "e",
    "s",
    "/",
    "c",
    "a",
    "r",
    "d",
    "s",
    "/",
    "1",
    "5",
    "6",
    "3",
    "5",
    "7",
    "5",
    "1",
    ".",
    "j",
    "p",
    "g"
  ],
  "type": "Spell",
  "spell_type": "Field"
}