{
  "id": 121191275,
  "name": "Crystal Transcendence",
  "is_illegal": false,
  "is_custom": true,
  "text": "[ Skill activation ]\nFlip this card over when you activate this Skill.\n[ Effect ]\nYou can only Summon/Set \"Crystal\" monsters and Dragon monsters while this Skill is face-up. Once per turn, during your Main Phase, you can send up to 3 cards from your hand to your GY, then choose that many \"Crystal Beast\" monster(s) with different names from your Deck and place them in your Spell & Trap Zone as Continuous Spell Card(s). This Skill can be used twice per Duel.",
  "images": [
    "https://images.ygoprodeck.com/images/cards/121191275.jpg"
  ],
  "type": "Spell",
  "spell_type": "Normal"
}