{
  "id": 131191654,
  "name": "D.D. King",
  "is_illegal": false,
  "is_custom": true,
  "text": "All \"D/D/D\" monsters you control gain 500 ATK until the end of the turn. This Skill can only be used once per turn and twice per Duel.\nIf you begin the Duel with a Deck/Extra Deck containing a total of 12 or more \"D/D/D\" monsters or \"Dark Contract\" Spell/Trap Cards, add Pendulum Zones to your field at the beginning of the Duel.",
  "images": [
    "h",
    "t",
    "t",
    "p",
    "s",
    ":",
    "/",
    "/",
    "i",
    "m",
    "a",
    "g",
    "e",
    "s",
    ".",
    "y",
    "g",
    "o",
    "p",
    "r",
    "o",
    "d",
    "e",
    "c",
    "k",
    ".",
    "c",
    "o",
    "m",
    "/",
    "i",
    "m",
    "a",
    "g",
    "e",
    "s",
    "/",
    "c",
    "a",
    "r",
    "d",
    "s",
    "/",
    "1",
    "3",
    "1",
    "1",
    "9",
    "1",
    "6",
    "5",
    "4",
    ".",
    "j",
    "p",
    "g"
  ],
  "type": "Spell",
  "spell_type": "Normal"
}