{
  "id": 130000082,
  "name": "Dark Scorpion - Tragedy of Love",
  "is_illegal": false,
  "is_custom": true,
  "text": "You can only activate this card when there are \"Don Zaloog\"and \"Dark Scorpion - Meanae the Thorn\" face-up on your side of the field. Send 1 \"Dark Scorpion - Meanae the Thorn\" from your side of your field to the Graveyard to destroy all of your opponent's monsters.",
  "images": [
    "https://images.ygoprodeck.com/images/cards/130000082.jpg"
  ],
  "type": "Spell",
  "spell_type": "Normal"
}