{
  "id": 131191678,
  "name": "Destiny Draw: Monster Reborn",
  "is_illegal": false,
  "is_custom": true,
  "text": "Can be used before your normal draw if your Life Points are at 2500 or below. Your normal draw this turn will be \"Monster Reborn\", from your Deck.\nIf your opponent controls a monster with 3000 ATK or more, you can use this Skill regardless of your Life Points. This Skill can only be used once per Duel.",
  "images": [
    "https://images.ygoprodeck.com/images/cards/131191678.jpg"
  ],
  "type": "Spell",
  "spell_type": "Normal"
}