{
  "id": 10032958,
  "name": "Divine Dragon - Excelion",
  "is_illegal": false,
  "is_custom": false,
  "text": "When this card is Normal Summoned, it gets 1 of the following effects for each \"Divine Dragon - Excelion\" in your Graveyard when this effect resolves (your choice). These effects cannot accumulate. \u25cf This card gains 1000 ATK. \u25cf If this card destroys an opponent's monster by battle, it can attack once again in a row. \u25cf When this card destroys a monster by battle and sends it to the Graveyard, inflict damage to your opponent equal to the ATK of the destroyed monster.",
  "images": [
    "https://images.ygoprodeck.com/images/cards/10032958.jpg"
  ],
  "type": "Monster",
  "attribute": "LIGHT",
  "atk": 1500,
  "species": "Dragon",
  "ability": "",
  "has_effect": true,
  "is_pendulum": false,
  "monster_type": "",
  "def": 900,
  "level": 5,
  "is_tuner": false
}