{
  "id": 60921537,
  "name": "Dogmatikamacabre",
  "is_illegal": false,
  "is_custom": false,
  "text": "This card can be used to Ritual Summon any \"Dogmatika\" Ritual Monster from your hand or GY. You must also Tribute monsters from your hand or field, and/or banish Fusion or Synchro Monsters from your GY, whose total Levels equal or exceed the Level of the Ritual Monster you Ritual Summon, then, if both \"White Knight of Dogmatika\" and \"White Relic of Dogmatika\" are on the field, you can look at either your Extra Deck or your opponent's, and send 1 monster from it to the GY. You can only activate 1 \"Dogmatikamacabre\" per turn.",
  "images": [
    "h",
    "t",
    "t",
    "p",
    "s",
    ":",
    "/",
    "/",
    "i",
    "m",
    "a",
    "g",
    "e",
    "s",
    ".",
    "y",
    "g",
    "o",
    "p",
    "r",
    "o",
    "d",
    "e",
    "c",
    "k",
    ".",
    "c",
    "o",
    "m",
    "/",
    "i",
    "m",
    "a",
    "g",
    "e",
    "s",
    "/",
    "c",
    "a",
    "r",
    "d",
    "s",
    "/",
    "6",
    "0",
    "9",
    "2",
    "1",
    "5",
    "3",
    "7",
    ".",
    "j",
    "p",
    "g"
  ],
  "type": "Spell",
  "spell_type": "Ritual"
}