{
  "id": 61204971,
  "name": "Elemental HERO Thunder Giant",
  "is_illegal": false,
  "is_custom": false,
  "text": "\"Elemental HERO Sparkman\" + \"Elemental HERO Clayman\"\nMust be Fusion Summoned and cannot be Special Summoned by other ways. Once per turn: You can discard 1 card to target 1 face-up monster on the field with original ATK less than the ATK of this card; destroy that target.",
  "images": [
    "https://images.ygoprodeck.com/images/cards/61204971.jpg"
  ],
  "type": "Monster",
  "monster_type": "Fusion",
  "attribute": "LIGHT",
  "atk": 2400,
  "def": 1500,
  "level": 6,
  "species": "Warrior",
  "has_effect": true,
  "is_pendulum": false,
  "is_tuner": false,
  "ability": ""
}