{
  "id": 54100561,
  "name": "FaSolfachord Fancia",
  "is_illegal": false,
  "is_custom": false,
  "text": "While you have an odd Pendulum Scale in your Pendulum Zone, if your \"Solfachord\" Pendulum Monster would be destroyed by battle, you can destroy this card instead. During your Main Phase: You can add 1 \"Solfachord\" Pendulum Monster from your Deck to your Extra Deck face-up, except \"FaSolfachord Fancia\". You can only use this effect of \"FaSolfachord Fancia\" once per turn.",
  "images": [
    "h",
    "t",
    "t",
    "p",
    "s",
    ":",
    "/",
    "/",
    "i",
    "m",
    "a",
    "g",
    "e",
    "s",
    ".",
    "y",
    "g",
    "o",
    "p",
    "r",
    "o",
    "d",
    "e",
    "c",
    "k",
    ".",
    "c",
    "o",
    "m",
    "/",
    "i",
    "m",
    "a",
    "g",
    "e",
    "s",
    "/",
    "c",
    "a",
    "r",
    "d",
    "s",
    "/",
    "5",
    "4",
    "1",
    "0",
    "0",
    "5",
    "6",
    "1",
    ".",
    "j",
    "p",
    "g"
  ],
  "type": "Monster",
  "attribute": "FIRE",
  "atk": 1600,
  "species": "Fairy",
  "ability": "",
  "has_effect": true,
  "monster_type": "",
  "is_pendulum": true,
  "pendulum_text": "Pendulum Summons of your \"Solfachord\" Pendulum Monsters cannot be negated.",
  "pendulum_scale_left_blue": 5,
  "pendulum_scale_right_red": 5,
  "def": 400,
  "level": 4,
  "is_tuner": false
}