{
  "id": 27132350,
  "name": "Fire Sorcerer",
  "is_illegal": false,
  "is_custom": false,
  "text": "FLIP: Banish 2 random cards from your hand; inflict 800 damage to your opponent.",
  "images": [
    "h",
    "t",
    "t",
    "p",
    "s",
    ":",
    "/",
    "/",
    "i",
    "m",
    "a",
    "g",
    "e",
    "s",
    ".",
    "y",
    "g",
    "o",
    "p",
    "r",
    "o",
    "d",
    "e",
    "c",
    "k",
    ".",
    "c",
    "o",
    "m",
    "/",
    "i",
    "m",
    "a",
    "g",
    "e",
    "s",
    "/",
    "c",
    "a",
    "r",
    "d",
    "s",
    "/",
    "2",
    "7",
    "1",
    "3",
    "2",
    "3",
    "5",
    "0",
    ".",
    "j",
    "p",
    "g"
  ],
  "type": "Monster",
  "attribute": "FIRE",
  "atk": 1000,
  "species": "Spellcaster",
  "ability": "Flip",
  "has_effect": true,
  "is_pendulum": false,
  "monster_type": "",
  "def": 1500,
  "level": 4,
  "is_tuner": false
}