{
  "id": 17760003,
  "name": "Genex Ally Triarm",
  "is_illegal": false,
  "is_custom": false,
  "text": "\"Genex Controller\" + 1 or more non-Tuner monsters\nThis card's effects depend on the Attribute(s) of its non-Tuner Synchro Material Monsters. Once per turn, you can discard 1 card to activate one of its effects: \u25cf WIND: Send 1 random card from your opponent's hand to the Graveyard. \u25cf WATER: Select 1 Spell/Trap Card on the field, and destroy it. \u25cf DARK: Select 1 face-up LIGHT monster on the field, destroy it and draw 1 card.",
  "images": [
    "h",
    "t",
    "t",
    "p",
    "s",
    ":",
    "/",
    "/",
    "i",
    "m",
    "a",
    "g",
    "e",
    "s",
    ".",
    "y",
    "g",
    "o",
    "p",
    "r",
    "o",
    "d",
    "e",
    "c",
    "k",
    ".",
    "c",
    "o",
    "m",
    "/",
    "i",
    "m",
    "a",
    "g",
    "e",
    "s",
    "/",
    "c",
    "a",
    "r",
    "d",
    "s",
    "/",
    "1",
    "7",
    "7",
    "6",
    "0",
    "0",
    "0",
    "3",
    ".",
    "j",
    "p",
    "g"
  ],
  "type": "Monster",
  "attribute": "DARK",
  "atk": 2400,
  "species": "Machine",
  "ability": "Synchro",
  "has_effect": true,
  "is_pendulum": false,
  "monster_type": "Synchro",
  "def": 1600,
  "level": 6,
  "is_tuner": false
}