{
  "id": 7617062,
  "name": "Ghostrick Museum",
  "is_illegal": false,
  "is_custom": false,
  "text": "Monsters you control, except \"Ghostrick\" monsters, cannot attack. Monsters cannot attack face-down Defense Position monsters, but can attack directly if all monsters their opponent controls are face-down Defense Position. At the end of the Damage Step, change any monster that inflicted battle damage to a player during this battle to face-down Defense Position.",
  "images": [
    "h",
    "t",
    "t",
    "p",
    "s",
    ":",
    "/",
    "/",
    "i",
    "m",
    "a",
    "g",
    "e",
    "s",
    ".",
    "y",
    "g",
    "o",
    "p",
    "r",
    "o",
    "d",
    "e",
    "c",
    "k",
    ".",
    "c",
    "o",
    "m",
    "/",
    "i",
    "m",
    "a",
    "g",
    "e",
    "s",
    "/",
    "c",
    "a",
    "r",
    "d",
    "s",
    "/",
    "7",
    "6",
    "1",
    "7",
    "0",
    "6",
    "2",
    ".",
    "j",
    "p",
    "g"
  ],
  "type": "Spell",
  "spell_type": "Field"
}