{
  "id": 47439573,
  "name": "Heartless Drop Off",
  "is_illegal": false,
  "is_custom": false,
  "text": "When a face-up card(s) on the field and/or in the GY is added to your opponent's hand by an effect: Look at their hand, also banish the added card(s) and all cards with the same name, if any.",
  "images": [
    "h",
    "t",
    "t",
    "p",
    "s",
    ":",
    "/",
    "/",
    "i",
    "m",
    "a",
    "g",
    "e",
    "s",
    ".",
    "y",
    "g",
    "o",
    "p",
    "r",
    "o",
    "d",
    "e",
    "c",
    "k",
    ".",
    "c",
    "o",
    "m",
    "/",
    "i",
    "m",
    "a",
    "g",
    "e",
    "s",
    "/",
    "c",
    "a",
    "r",
    "d",
    "s",
    "/",
    "4",
    "7",
    "4",
    "3",
    "9",
    "5",
    "7",
    "3",
    ".",
    "j",
    "p",
    "g"
  ],
  "type": "Trap",
  "trap_type": "Counter"
}