{
  "id": 48546368,
  "name": "Herald of Ultimateness",
  "is_illegal": false,
  "is_custom": false,
  "text": "You can Ritual Summon this card with \"Oracle of the Herald\". Must be Ritual Summoned. When your opponent would Special Summon a monster(s), OR activates a Spell/Trap Card, or a monster effect (Quick Effect): You can send 1 Fairy monster from your hand to the GY; negate the Special Summon or activation, and if you do, destroy that card.",
  "images": [
    "h",
    "t",
    "t",
    "p",
    "s",
    ":",
    "/",
    "/",
    "i",
    "m",
    "a",
    "g",
    "e",
    "s",
    ".",
    "y",
    "g",
    "o",
    "p",
    "r",
    "o",
    "d",
    "e",
    "c",
    "k",
    ".",
    "c",
    "o",
    "m",
    "/",
    "i",
    "m",
    "a",
    "g",
    "e",
    "s",
    "/",
    "c",
    "a",
    "r",
    "d",
    "s",
    "/",
    "4",
    "8",
    "5",
    "4",
    "6",
    "3",
    "6",
    "8",
    ".",
    "j",
    "p",
    "g"
  ],
  "type": "Monster",
  "attribute": "LIGHT",
  "atk": 2000,
  "species": "Fairy",
  "ability": "",
  "has_effect": true,
  "is_pendulum": false,
  "monster_type": "Ritual",
  "def": 3000,
  "level": 12,
  "is_tuner": false
}