{
  "id": 90934570,
  "name": "Infestation Terminus",
  "is_illegal": false,
  "is_custom": false,
  "text": "Target 1 \"lswarm\" monster you control and 2 cards your opponent controls; banish the first target, and if you do, return the second targets to the hand.",
  "images": [
    "h",
    "t",
    "t",
    "p",
    "s",
    ":",
    "/",
    "/",
    "i",
    "m",
    "a",
    "g",
    "e",
    "s",
    ".",
    "y",
    "g",
    "o",
    "p",
    "r",
    "o",
    "d",
    "e",
    "c",
    "k",
    ".",
    "c",
    "o",
    "m",
    "/",
    "i",
    "m",
    "a",
    "g",
    "e",
    "s",
    "/",
    "c",
    "a",
    "r",
    "d",
    "s",
    "/",
    "9",
    "0",
    "9",
    "3",
    "4",
    "5",
    "7",
    "0",
    ".",
    "j",
    "p",
    "g"
  ],
  "type": "Trap",
  "trap_type": "Normal"
}