{
  "id": 130000088,
  "name": "Inviting Cat",
  "is_illegal": false,
  "is_custom": true,
  "text": "Add 1 \"Cat Girl\" monster or \"Stray Cat\" monster from your Deck to your hand.",
  "images": [
    "h",
    "t",
    "t",
    "p",
    "s",
    ":",
    "/",
    "/",
    "i",
    "m",
    "a",
    "g",
    "e",
    "s",
    ".",
    "y",
    "g",
    "o",
    "p",
    "r",
    "o",
    "d",
    "e",
    "c",
    "k",
    ".",
    "c",
    "o",
    "m",
    "/",
    "i",
    "m",
    "a",
    "g",
    "e",
    "s",
    "/",
    "c",
    "a",
    "r",
    "d",
    "s",
    "/",
    "1",
    "3",
    "0",
    "0",
    "0",
    "0",
    "0",
    "8",
    "8",
    ".",
    "j",
    "p",
    "g"
  ],
  "type": "Spell",
  "spell_type": "Normal"
}