{
  "id": 150001450,
  "name": "Invisibility",
  "is_illegal": false,
  "is_custom": true,
  "text": "Target 1 monster you control; this turn, it cannot be targeted by your opponent's card effects, also it is unaffected by other card effects.",
  "images": [
    "h",
    "t",
    "t",
    "p",
    "s",
    ":",
    "/",
    "/",
    "i",
    "m",
    "a",
    "g",
    "e",
    "s",
    ".",
    "y",
    "g",
    "o",
    "p",
    "r",
    "o",
    "d",
    "e",
    "c",
    "k",
    ".",
    "c",
    "o",
    "m",
    "/",
    "i",
    "m",
    "a",
    "g",
    "e",
    "s",
    "/",
    "c",
    "a",
    "r",
    "d",
    "s",
    "/",
    "1",
    "5",
    "0",
    "0",
    "0",
    "1",
    "4",
    "5",
    "0",
    ".",
    "j",
    "p",
    "g"
  ],
  "type": "Spell",
  "spell_type": "Quick-Play"
}