{
  "id": 7127502,
  "name": "Lector Pendulum, the Dracoverlord",
  "is_illegal": false,
  "is_custom": false,
  "text": "[ Pendulum Effect ] \nNegate the effects of face-up Pendulum Monsters while your opponent controls them.\n\n[ Monster Effect ] \nAt the start of the Damage Step, if this card battles a Pendulum Monster: Destroy both that monster and this card.",
  "images": [
    "https://images.ygoprodeck.com/images/cards/7127502.jpg"
  ],
  "type": "Monster",
  "monster_type": "Effect",
  "attribute": "DARK",
  "atk": 1950,
  "def": 0,
  "level": 4,
  "species": "Dragon",
  "has_effect": true,
  "is_pendulum": true,
  "is_tuner": false,
  "ability": ""
}