{
  "id": 511003037,
  "name": "Magical Hats",
  "is_illegal": false,
  "is_custom": true,
  "text": "During your opponent's Battle Phase: Choose 2 Spells/Traps from your Deck and 1 monster you control. Special Summon them as Normal Monsters (ATK 0/DEF 0) in face-down Defense Position, Set the chosen monster if it is face-up, and shuffle them on the field. The 2 cards chosen from your Deck are destroyed at the end of the Battle Phase, and cannot remain on the field except during this Battle Phase.",
  "images": [
    "h",
    "t",
    "t",
    "p",
    "s",
    ":",
    "/",
    "/",
    "i",
    "m",
    "a",
    "g",
    "e",
    "s",
    ".",
    "y",
    "g",
    "o",
    "p",
    "r",
    "o",
    "d",
    "e",
    "c",
    "k",
    ".",
    "c",
    "o",
    "m",
    "/",
    "i",
    "m",
    "a",
    "g",
    "e",
    "s",
    "/",
    "c",
    "a",
    "r",
    "d",
    "s",
    "/",
    "5",
    "1",
    "1",
    "0",
    "0",
    "3",
    "0",
    "3",
    "7",
    ".",
    "j",
    "p",
    "g"
  ],
  "type": "Trap",
  "trap_type": "Normal"
}