{
  "id": 98494543,
  "name": "Magical Stone Excavation",
  "is_illegal": false,
  "is_custom": false,
  "text": "Discard 2 cards, then target 1 Spell in your GY; add it to your hand.",
  "images": [
    "h",
    "t",
    "t",
    "p",
    "s",
    ":",
    "/",
    "/",
    "i",
    "m",
    "a",
    "g",
    "e",
    "s",
    ".",
    "y",
    "g",
    "o",
    "p",
    "r",
    "o",
    "d",
    "e",
    "c",
    "k",
    ".",
    "c",
    "o",
    "m",
    "/",
    "i",
    "m",
    "a",
    "g",
    "e",
    "s",
    "/",
    "c",
    "a",
    "r",
    "d",
    "s",
    "/",
    "9",
    "8",
    "4",
    "9",
    "4",
    "5",
    "4",
    "3",
    ".",
    "j",
    "p",
    "g"
  ],
  "type": "Spell",
  "spell_type": "Normal"
}