{
  "id": 78949372,
  "name": "Majespecter Supercell",
  "is_illegal": false,
  "is_custom": false,
  "text": "While you have a \"Majespecter\" card in your Pendulum Zone, the activation and effects of other \"Majespecter\" cards activated on your side of the field cannot be negated. Once per turn: You can target 5 \"Majespecter\" cards in your Graveyard; shuffle all 5 into the Deck, then draw 1 card.",
  "images": [
    "h",
    "t",
    "t",
    "p",
    "s",
    ":",
    "/",
    "/",
    "i",
    "m",
    "a",
    "g",
    "e",
    "s",
    ".",
    "y",
    "g",
    "o",
    "p",
    "r",
    "o",
    "d",
    "e",
    "c",
    "k",
    ".",
    "c",
    "o",
    "m",
    "/",
    "i",
    "m",
    "a",
    "g",
    "e",
    "s",
    "/",
    "c",
    "a",
    "r",
    "d",
    "s",
    "/",
    "7",
    "8",
    "9",
    "4",
    "9",
    "3",
    "7",
    "2",
    ".",
    "j",
    "p",
    "g"
  ],
  "type": "Trap",
  "trap_type": "Continuous"
}