{
  "id": 59305593,
  "name": "Mistake",
  "is_illegal": false,
  "is_custom": false,
  "text": "Neither player can add cards from their Deck to their hand except by drawing them.",
  "images": [
    "h",
    "t",
    "t",
    "p",
    "s",
    ":",
    "/",
    "/",
    "i",
    "m",
    "a",
    "g",
    "e",
    "s",
    ".",
    "y",
    "g",
    "o",
    "p",
    "r",
    "o",
    "d",
    "e",
    "c",
    "k",
    ".",
    "c",
    "o",
    "m",
    "/",
    "i",
    "m",
    "a",
    "g",
    "e",
    "s",
    "/",
    "c",
    "a",
    "r",
    "d",
    "s",
    "/",
    "5",
    "9",
    "3",
    "0",
    "5",
    "5",
    "9",
    "3",
    ".",
    "j",
    "p",
    "g"
  ],
  "type": "Trap",
  "trap_type": "Continuous"
}