{
  "id": 13629812,
  "name": "Ninjitsu Art of Shadow Sealing",
  "is_illegal": false,
  "is_custom": false,
  "text": "Tribute 1 \"Ninja\" monster to target 1 monster your opponent controls; banish that target. While that card is banished, its Monster Card Zone cannot be used. When this face-up card leaves the field: Return the card banished by this effect to the same Monster Card Zone, in the same battle position.",
  "images": [
    "h",
    "t",
    "t",
    "p",
    "s",
    ":",
    "/",
    "/",
    "i",
    "m",
    "a",
    "g",
    "e",
    "s",
    ".",
    "y",
    "g",
    "o",
    "p",
    "r",
    "o",
    "d",
    "e",
    "c",
    "k",
    ".",
    "c",
    "o",
    "m",
    "/",
    "i",
    "m",
    "a",
    "g",
    "e",
    "s",
    "/",
    "c",
    "a",
    "r",
    "d",
    "s",
    "/",
    "1",
    "3",
    "6",
    "2",
    "9",
    "8",
    "1",
    "2",
    ".",
    "j",
    "p",
    "g"
  ],
  "type": "Trap",
  "trap_type": "Continuous"
}