{
  "id": 68477598,
  "name": "Pendulum Hole",
  "is_illegal": false,
  "is_custom": false,
  "text": "When a monster(s) would be Pendulum Summoned: Negate the Pendulum Summon, and if you do, shuffle that monster(s) into the Deck.",
  "images": [
    "h",
    "t",
    "t",
    "p",
    "s",
    ":",
    "/",
    "/",
    "i",
    "m",
    "a",
    "g",
    "e",
    "s",
    ".",
    "y",
    "g",
    "o",
    "p",
    "r",
    "o",
    "d",
    "e",
    "c",
    "k",
    ".",
    "c",
    "o",
    "m",
    "/",
    "i",
    "m",
    "a",
    "g",
    "e",
    "s",
    "/",
    "c",
    "a",
    "r",
    "d",
    "s",
    "/",
    "6",
    "8",
    "4",
    "7",
    "7",
    "5",
    "9",
    "8",
    ".",
    "j",
    "p",
    "g"
  ],
  "type": "Trap",
  "trap_type": "Counter"
}