{
  "id": 64450427,
  "name": "Performapal Whim Witch",
  "is_illegal": false,
  "is_custom": false,
  "text": "This card can be treated as 2 Tributes for the Tribute Summon of a Pendulum Monster.",
  "images": [
    "h",
    "t",
    "t",
    "p",
    "s",
    ":",
    "/",
    "/",
    "i",
    "m",
    "a",
    "g",
    "e",
    "s",
    ".",
    "y",
    "g",
    "o",
    "p",
    "r",
    "o",
    "d",
    "e",
    "c",
    "k",
    ".",
    "c",
    "o",
    "m",
    "/",
    "i",
    "m",
    "a",
    "g",
    "e",
    "s",
    "/",
    "c",
    "a",
    "r",
    "d",
    "s",
    "/",
    "6",
    "4",
    "4",
    "5",
    "0",
    "4",
    "2",
    "7",
    ".",
    "j",
    "p",
    "g"
  ],
  "type": "Monster",
  "attribute": "DARK",
  "atk": 800,
  "species": "Spellcaster",
  "ability": "",
  "has_effect": true,
  "monster_type": "",
  "is_pendulum": true,
  "pendulum_text": "If your opponent controls a face-up monster that was Special Summoned from the Extra Deck and you do not: You can Special Summon this card from your Pendulum Zone. You can only use this effect of \"Performapal Whim Witch\" once per turn.",
  "pendulum_scale_left_blue": 4,
  "pendulum_scale_right_red": 4,
  "def": 800,
  "level": 3,
  "is_tuner": false
}