{
  "id": 22091345,
  "name": "Performapal Spikeagle",
  "is_illegal": false,
  "is_custom": false,
  "text": "Once per turn: You can target 1 face-up monster you control; if it attacks a Defense Position monster this turn, inflict piercing battle damage to your opponent.",
  "images": [
    "https://images.ygoprodeck.com/images/cards/22091345.jpg"
  ],
  "type": "Monster",
  "attribute": "WIND",
  "atk": 900,
  "species": "Winged Beast",
  "ability": "",
  "has_effect": true,
  "is_pendulum": false,
  "monster_type": "",
  "def": 900,
  "level": 2,
  "is_tuner": false
}