{
  "id": 71353388,
  "name": "Reed Butterfly",
  "is_illegal": false,
  "is_custom": false,
  "text": "If your opponent controls a face-up Synchro Monster(s) and you control no face-up Synchro Monsters, you can Special Summon this card from your hand.",
  "images": [
    "h",
    "t",
    "t",
    "p",
    "s",
    ":",
    "/",
    "/",
    "i",
    "m",
    "a",
    "g",
    "e",
    "s",
    ".",
    "y",
    "g",
    "o",
    "p",
    "r",
    "o",
    "d",
    "e",
    "c",
    "k",
    ".",
    "c",
    "o",
    "m",
    "/",
    "i",
    "m",
    "a",
    "g",
    "e",
    "s",
    "/",
    "c",
    "a",
    "r",
    "d",
    "s",
    "/",
    "7",
    "1",
    "3",
    "5",
    "3",
    "3",
    "8",
    "8",
    ".",
    "j",
    "p",
    "g"
  ],
  "type": "Monster",
  "attribute": "WIND",
  "atk": 300,
  "species": "Insect",
  "ability": "",
  "has_effect": true,
  "is_pendulum": false,
  "monster_type": "",
  "def": 600,
  "level": 1,
  "is_tuner": false
}