{
  "id": 4939890,
  "name": "Shaddoll Hedgehog",
  "is_illegal": false,
  "is_custom": false,
  "text": "FLIP: You can add 1 \"Shaddoll\" Spell/Trap from your Deck to your hand.\nIf this card is sent to the GY by a card effect: You can add 1 \"Shaddoll\" monster from your Deck to your hand, except \"Shaddoll Hedgehog\". You can only use 1 \"Shaddoll Hedgehog\" effect per turn, and only once that turn.",
  "images": [
    "h",
    "t",
    "t",
    "p",
    "s",
    ":",
    "/",
    "/",
    "i",
    "m",
    "a",
    "g",
    "e",
    "s",
    ".",
    "y",
    "g",
    "o",
    "p",
    "r",
    "o",
    "d",
    "e",
    "c",
    "k",
    ".",
    "c",
    "o",
    "m",
    "/",
    "i",
    "m",
    "a",
    "g",
    "e",
    "s",
    "/",
    "c",
    "a",
    "r",
    "d",
    "s",
    "/",
    "4",
    "9",
    "3",
    "9",
    "8",
    "9",
    "0",
    ".",
    "j",
    "p",
    "g"
  ],
  "type": "Monster",
  "attribute": "DARK",
  "atk": 800,
  "species": "Spellcaster",
  "ability": "Flip",
  "has_effect": true,
  "is_pendulum": false,
  "monster_type": "",
  "def": 200,
  "level": 3,
  "is_tuner": false
}