{
  "id": 81810441,
  "name": "Stellarknight Alpha",
  "is_illegal": false,
  "is_custom": false,
  "text": "Equip only to a \"tellarknight\" monster you control. It gains 500 ATK and DEF, also it is unaffected by your opponent's card effects. If you control a face-up monster that is not a \"tellarknight\" monster, destroy this card.",
  "images": [
    "h",
    "t",
    "t",
    "p",
    "s",
    ":",
    "/",
    "/",
    "i",
    "m",
    "a",
    "g",
    "e",
    "s",
    ".",
    "y",
    "g",
    "o",
    "p",
    "r",
    "o",
    "d",
    "e",
    "c",
    "k",
    ".",
    "c",
    "o",
    "m",
    "/",
    "i",
    "m",
    "a",
    "g",
    "e",
    "s",
    "/",
    "c",
    "a",
    "r",
    "d",
    "s",
    "/",
    "8",
    "1",
    "8",
    "1",
    "0",
    "4",
    "4",
    "1",
    ".",
    "j",
    "p",
    "g"
  ],
  "type": "Spell",
  "spell_type": "Equip"
}