{
  "id": 131192014,
  "name": "Sunavalon Luxuriance",
  "is_illegal": false,
  "is_custom": true,
  "text": "You can only use this Skill's second effect once per turn.\n1: At the beginning of the Duel, if all of the monsters in your Extra Deck are Link Monsters with different names, add 5 \"Sunavalon\" monsters with different names to your Extra Deck, also for the rest of this Duel, you cannot Special Summon monsters, except EARTH Plant monsters or Link Monsters.\n2: Shuffle 1 \"Sunavalon\" monster, \"Sunvine\" monster, or \"Sunseed\" monster from your hand into the Deck, then add 1 \"Sunseed Genius Loci\" from your Deck, Graveyard, or among your banished cards to your hand.",
  "images": [
    "https://images.ygoprodeck.com/images/cards/131192014.jpg"
  ],
  "type": "Spell",
  "spell_type": "Normal"
}