{
  "id": 61405855,
  "name": "Sword of Dragon's Soul",
  "is_illegal": false,
  "is_custom": false,
  "text": "Equip only to a Warrior monster. It gains 700 ATK. After damage calculation, if the equipped monster battled a Dragon monster: Destroy that monster at the end of that Battle Phase.",
  "images": [
    "h",
    "t",
    "t",
    "p",
    "s",
    ":",
    "/",
    "/",
    "i",
    "m",
    "a",
    "g",
    "e",
    "s",
    ".",
    "y",
    "g",
    "o",
    "p",
    "r",
    "o",
    "d",
    "e",
    "c",
    "k",
    ".",
    "c",
    "o",
    "m",
    "/",
    "i",
    "m",
    "a",
    "g",
    "e",
    "s",
    "/",
    "c",
    "a",
    "r",
    "d",
    "s",
    "/",
    "6",
    "1",
    "4",
    "0",
    "5",
    "8",
    "5",
    "5",
    ".",
    "j",
    "p",
    "g"
  ],
  "type": "Spell",
  "spell_type": "Equip"
}