{
  "id": 131191812,
  "name": "Timelord Booster",
  "is_illegal": false,
  "is_custom": true,
  "text": "Select 1 \"Timelord\" monster you control, and increase its ATK by its Level x200 until the end of the turn. During this turn, your opponent takes no battle damage from attacks involving the selected monster.\nThis Skill can only be used once per turn and twice per Duel.",
  "images": [
    "https://images.ygoprodeck.com/images/cards/131191812.jpg"
  ],
  "type": "Spell",
  "spell_type": "Normal"
}