{
  "id": 2333365,
  "name": "Tyr of the Nordic Champions",
  "is_illegal": false,
  "is_custom": false,
  "text": "Your opponent's monsters cannot target \"Nordic\" monsters for attacks, except \"Tyr of the Nordic Champions\". If there is no other \"Nordic\" monster on the field, destroy this card.",
  "images": [
    "h",
    "t",
    "t",
    "p",
    "s",
    ":",
    "/",
    "/",
    "i",
    "m",
    "a",
    "g",
    "e",
    "s",
    ".",
    "y",
    "g",
    "o",
    "p",
    "r",
    "o",
    "d",
    "e",
    "c",
    "k",
    ".",
    "c",
    "o",
    "m",
    "/",
    "i",
    "m",
    "a",
    "g",
    "e",
    "s",
    "/",
    "c",
    "a",
    "r",
    "d",
    "s",
    "/",
    "2",
    "3",
    "3",
    "3",
    "3",
    "6",
    "5",
    ".",
    "j",
    "p",
    "g"
  ],
  "type": "Monster",
  "attribute": "LIGHT",
  "atk": 2000,
  "species": "Warrior",
  "ability": "",
  "has_effect": true,
  "is_pendulum": false,
  "monster_type": "",
  "def": 2000,
  "level": 4,
  "is_tuner": false
}