{
  "id": 51638941,
  "name": "V-Tiger Jet",
  "is_illegal": false,
  "is_custom": false,
  "text": "This ace fighter is unbeatable in a dogfight. It combines with other monsters to launch an array of encircling attacks.",
  "images": [
    "h",
    "t",
    "t",
    "p",
    "s",
    ":",
    "/",
    "/",
    "i",
    "m",
    "a",
    "g",
    "e",
    "s",
    ".",
    "y",
    "g",
    "o",
    "p",
    "r",
    "o",
    "d",
    "e",
    "c",
    "k",
    ".",
    "c",
    "o",
    "m",
    "/",
    "i",
    "m",
    "a",
    "g",
    "e",
    "s",
    "/",
    "c",
    "a",
    "r",
    "d",
    "s",
    "/",
    "5",
    "1",
    "6",
    "3",
    "8",
    "9",
    "4",
    "1",
    ".",
    "j",
    "p",
    "g"
  ],
  "type": "Monster",
  "attribute": "LIGHT",
  "atk": 1600,
  "species": "Machine",
  "ability": "",
  "has_effect": false,
  "is_pendulum": false,
  "monster_type": "",
  "def": 1800,
  "level": 4,
  "is_tuner": false
}