{
  "id": 62499965,
  "name": "Z-ONE",
  "is_illegal": false,
  "is_custom": false,
  "text": "If this Set card is destroyed and sent to the GY: Target 1 Continuous Spell or Field Spell in your GY; add it to your hand.",
  "images": [
    "h",
    "t",
    "t",
    "p",
    "s",
    ":",
    "/",
    "/",
    "i",
    "m",
    "a",
    "g",
    "e",
    "s",
    ".",
    "y",
    "g",
    "o",
    "p",
    "r",
    "o",
    "d",
    "e",
    "c",
    "k",
    ".",
    "c",
    "o",
    "m",
    "/",
    "i",
    "m",
    "a",
    "g",
    "e",
    "s",
    "/",
    "c",
    "a",
    "r",
    "d",
    "s",
    "/",
    "6",
    "2",
    "4",
    "9",
    "9",
    "9",
    "6",
    "5",
    ".",
    "j",
    "p",
    "g"
  ],
  "type": "Spell",
  "spell_type": "Normal"
}